{
  "DatePicker": {
    "value": "`Date \\ | Date[]` — 选中的值",
    "placeholder": "`string` — 占位符",
    "formatter": "`(value: Date \\ | Date[]) => string` — 格式化函数",
    "autoSize": "`boolean` — 自动调整大小",
    "separator": "`string` — 分隔符",
    "readOnly": "`boolean` — 是否只读",
    "disabled": "`boolean` — 是否禁用",
    "allowClear": "`boolean` — 允许清除",
    "style": "`object` — 自定义样式",
    "className": "`string` — 自定义类名",
    "comboRender": "`() => ReactNode` — 自定义组合渲染",
    "children": "`ReactNode` — 子元素",
    "leftIconNode": "`ReactNode` — 左侧图标",
    "rightIconNode": "`ReactNode` — 右侧图标",
    "clearRender": "`(props: object) => ReactNode` — 清除按钮渲染",
    "type": "`'year' \\ | 'quarter' \\ | 'month' \\ | 'date' \\ | 'time' \\ | 'datetime' \\ | 'week'` — 日期类型，默认 `'date'`",
    "min": "`Date` — 最小日期",
    "max": "`Date` — 最大日期",
    "hourStep": "`number` — 小时步长",
    "minuteStep": "`number` — 分钟步长",
    "maskClosable": "`boolean` — 点击遮罩关闭",
    "safeArea": "`boolean` — 是否安全区",
    "modalStyle": "`object` — 模态框样式",
    "modalClassName": "`string` — 模态框类名",
    "maskStyle": "`object` — 遮罩样式",
    "maskClassName": "`string` — 遮罩类名",
    "portal": "`HTMLElement \\ | null \\ | false` — 挂载节点",
    "titleRender": "`() => ReactNode` — 标题渲染",
    "okNode": "`ReactNode` — 确认按钮",
    "cancelNode": "`ReactNode` — 取消按钮",
    "okVisible": "`boolean` — 确认按钮可见",
    "cancelVisible": "`boolean` — 取消按钮可见",
    "onBeforeOpen": "`() => Promise<boolean>` — 打开前事件",
    "onChange": "`(value: Date \\ | Date[]) => void` — 变化事件",
    "onOk": "`(value: Date \\ | Date[]) => void` — 确认事件"
  },
  "DatePicker.TypeSwitcher": {
    "value": "`object` — 当前选中项",
    "types": "`Array<object>` — 类型列表",
    "switcherType": "`'tabbar' \\ | 'dropdown'` — 切换方式",
    "dropdownPortal": "`HTMLElement` — 下拉挂载节点",
    "style": "`object` — 自定义样式",
    "className": "`string` — 自定义类名",
    "pickerComboStyle": "`object` — 选择器组合样式",
    "pickerComboClassName": "`string` — 选择器组合类名",
    "tabbarStyle": "`object` — Tab 栏样式",
    "tabbarClassName": "`string` — Tab 栏类名",
    "min": "`Date \\ | null` — 最小日期",
    "max": "`Date \\ | null` — 最大日期",
    "pickerComboRender": "`(value: object, ctx: object) => ReactNode` — 选择器组合渲染",
    "onChange": "`(value: object) => void` — 变化事件"
  },
  "DatePicker.RangeSelector": {
    "value": "`(Date \\ | null)[] \\ | null` — 选中的值",
    "autoSwapValue": "`boolean` — 自动交换值，默认 `true`",
    "type": "`'year' \\ | 'quarter' \\ | 'month' \\ | 'date' \\ | 'time' \\ | 'datetime'` — 日期类型，默认 `'date'`",
    "rangeId": "`string` — 当前选中的范围",
    "ranges": "`object` — 范围配置",
    "min": "`Date` — 最小日期",
    "max": "`Date` — 最大日期",
    "hourStep": "`number` — 小时步长",
    "minuteStep": "`number` — 分钟步长",
    "startDisabled": "`boolean` — 禁用开始日期",
    "endDisabled": "`boolean` — 禁用结束日期",
    "allowClear": "`boolean` — 允许清除",
    "style": "`object` — 自定义样式",
    "className": "`string` — 自定义类名",
    "portal": "`HTMLElement` — 挂载节点",
    "onChange": "`(value: (Date \\ | null)[] \\ | null, meta?: object) => void` — 变化事件",
    "onOk": "`(value: (Date \\ | null)[] \\ | null) => void` — 确认事件"
  },
  "DatePicker.ref": {
    "element": "`HTMLDivElement` — 根元素",
    "getElement": "() => `HTMLDivElement` — 获取根元素",
    "close": "`() => void` — 关闭选择器",
    "open": "`() => void` — 打开选择器"
  },
  "DatePicker.TypeSwitcher.ref": {
    "element": "`HTMLDivElement` — 根元素",
    "getElement": "() => `HTMLDivElement` — 获取根元素"
  }
}
